ringcentral_bot_framework/__init__.py
ringcentral_bot_framework/core/__init__.py
ringcentral_bot_framework/core/bot.py
ringcentral_bot_framework/core/bot_oauth.py
ringcentral_bot_framework/core/bot_webhook.py
ringcentral_bot_framework/core/common.py
ringcentral_bot_framework/core/config.py
ringcentral_bot_framework/core/config_default.py
ringcentral_bot_framework/core/data.py
ringcentral_bot_framework/core/db.py
ringcentral_bot_framework/core/dynamodb.py
ringcentral_bot_framework/core/extensions.py
ringcentral_bot_framework/core/filedb.py
ringcentral_bot_framework/core/flask_request_parser.py
ringcentral_bot_framework/core/hidden_cmd.py
ringcentral_bot_framework/core/interactive.py
ringcentral_bot_framework/core/route.py
ringcentral_bot_framework/core/self_run.py
ringcentral_bot_framework/core/user.py
ringcentral_bot_framework/core/user_oauth.py
ringcentral_bot_framework/core/user_webhook.py
ringcentral_bot_framework-0.7.2.dist-info/LICENSE
ringcentral_bot_framework-0.7.2.dist-info/METADATA
ringcentral_bot_framework-0.7.2.dist-info/WHEEL
ringcentral_bot_framework-0.7.2.dist-info/top_level.txt
ringcentral_bot_framework-0.7.2.dist-info/RECORD
