Metadata-Version: 2.1
Name: ringcentral-bot-framework
Version: 0.7.2
Summary: RingCentral Chatbot Framework for Python
Home-page: https://github.com/ringcentral/ringcentral-chatbot-python
Author: Drake Zhao @ RingCentral
Author-email: drake.zhao@ringcentral.com
License: UNKNOWN
Keywords: ringcentral,bot,framework
Platform: UNKNOWN
Classifier: Programming Language :: Python :: 3
Classifier: License :: OSI Approved :: MIT License
Classifier: Operating System :: OS Independent
Requires-Dist: ringcentral-client
Requires-Dist: pydash
